{"inkVersion":20,"root":[["\n","ev",{"VAR?":"wistful_current_dialogue"},"str","^","/str","==","/ev",[{"->":".^.b","c":true},{"b":["^ ",{"->":"wistful_first_talk"},{"->":"0.9"},null]}],"nop","\n","ev",{"VAR?":"wistful_current_dialogue"},"str","^2","/str","==","/ev",[{"->":".^.b","c":true},{"b":["^ ",{"->":"wistful_second_talk"},{"->":"0.19"},null]}],"nop","\n","ev",{"VAR?":"wistful_current_dialogue"},"str","^3","/str","==","/ev",[{"->":".^.b","c":true},{"b":["^ ",{"->":"wistful_third_talk"},{"->":"0.29"},null]}],"nop","\n","ev",{"VAR?":"wistful_current_dialogue"},"str","^4","/str","==","/ev",[{"->":".^.b","c":true},{"b":["^ ",{"->":"wistful_fourth_talk"},{"->":"0.39"},null]}],"nop","\n","ev",{"VAR?":"wistful_current_dialogue"},"str","^5","/str","==","/ev",[{"->":".^.b","c":true},{"b":["^ ",{"->":"wistful_final_talk"},{"->":"0.49"},null]}],"nop","\n",["done",{"#f":5,"#n":"g-0"}],null],"done",{"wistful_first_talk":["^Hello, would you sit with me a while? I could use the company. ",{"#":"speaker:Wistful Woman"},{"#":"portrait:npc8_neutral"},{"#":"layout:left"},{"#":"character:npc8"},"\n","^Of course. ",{"#":"speaker: Peyton"},{"#":"portrait:mc_happy"},{"#":"layout:right"},"\n","^Headed to the city for a big event? ",{"#":"speaker: Peyton"},{"#":"portrait:mc_happy"},{"#":"layout:right"},"\n","^No, I’m afraid the city is not even my end destination, just one of many stops along the way. ",{"#":"speaker:Wistful Woman"},{"#":"portrait:npc8_neutral"},{"#":"layout:left"},"\n","^Are you travelling entirely by train? That’s a long journey! ",{"#":"speaker: Peyton"},{"#":"portrait:mc_happy"},{"#":"layout:right"},"\n","^It’s not all by train. Train, plane, boat. ",{"#":"speaker:Wistful Woman"},{"#":"portrait:npc8_neutral"},{"#":"layout:left"},"\n","^Wow, that’s a lot of travelling. Where are you going? ",{"#":"speaker: Peyton"},{"#":"portrait:mc_happy"},{"#":"layout:right"},"\n","^I’m not really going anywhere, but also I am going everywhere. ",{"#":"speaker:Wistful Woman"},{"#":"portrait:npc8_neutral"},{"#":"layout:left"},"\n","^I’m a travelling ambassador. So I go from city, to town, from region, to county to wherever I am needed to go. ",{"#":"speaker:Wistful Woman"},{"#":"portrait:npc8_neutral"},{"#":"layout:left"},"\n","^That’s so exciting! You must meet so many people. ",{"#":"speaker: Peyton"},{"#":"portrait:mc_happy"},{"#":"layout:right"},"\n","^I do! I do… It is all very exciting. Many places to go, many people to meet. ",{"#":"speaker:Wistful Woman"},{"#":"portrait:npc8_neutral"},{"#":"layout:left"},"\n","^Do you like what you do? ",{"#":"speaker: Peyton"},{"#":"portrait:mc_happy"},{"#":"layout:right"},"\n","^Hmm? ",{"#":"speaker:Wistful Woman"},{"#":"portrait:npc8_neutral"},{"#":"layout:left"},"\n","^May we just sit in silence for a while? I would enjoy that very much. ",{"#":"speaker:Wistful Woman"},{"#":"portrait:npc8_neutral"},{"#":"layout:left"},"\n","^Oh. Okay. ",{"#":"speaker: Peyton"},{"#":"portrait:mc_upset"},{"#":"layout:right"},"\n","^Thank you. … ",{"#":"speaker:Wistful Woman"},{"#":"portrait:npc8_happy"},{"#":"layout:left"},"\n","^… ",{"#":"speaker:Wistful Woman"},{"#":"portrait:npc8_neutral"},{"#":"layout:left"},"\n","ev","str","^2","/str","/ev",{"VAR=":"wistful_current_dialogue","re":true},"end",{"#f":1}],"wistful_second_talk":["^So is it exciting travelling around a lot? Where are your favourite places to go? ",{"#":"speaker: Peyton"},{"#":"portrait:mc_happy"},{"#":"layout:right"},{"#":"character:npc8"},"\n","^I do like to find a nice small cafe or restaurant in many of the cities that I visit, someplace with good coffee and a quiet ambience. ",{"#":"speaker:Wistful Woman"},{"#":"portrait:npc8_neutral"},{"#":"layout:left"},"\n","^I’m afraid I travel so much that the veneer of excitement has gone from travelling for me, it’s just work. ",{"#":"speaker:Wistful Woman"},{"#":"portrait:npc8_neutral"},{"#":"layout:left"},"\n","^Oh.. I figure it would be exciting getting to go to different places, experiences, new sights and things. ",{"#":"speaker: Peyton"},{"#":"portrait:mc_sad"},{"#":"layout:right"},"\n","^It would be, but I’m always there for work and not for a long time, so I have a short timeframe to actually enjoy a city. It’s often more work trying to have fun. ",{"#":"speaker:Wistful Woman"},{"#":"portrait:npc8_neutral"},{"#":"layout:left"},"\n","^Ah… I bet coming home is nice then! ",{"#":"speaker: Peyton"},{"#":"portrait:mc_happy"},{"#":"layout:right"},"\n","^It is at times. I am away more than I am home so home is just another stop on the road for me. ",{"#":"speaker:Wistful Woman"},{"#":"portrait:npc8_neutral"},{"#":"layout:left"},"\n","^That sounds… hectic. ",{"#":"speaker: Peyton"},{"#":"portrait:mc_sad"},{"#":"layout:right"},"\n","^It is. ",{"#":"speaker:Wistful Woman"},{"#":"portrait:npc8_neutral"},{"#":"layout:left"},"\n","^I try to get the quiet moments in when I can. ",{"#":"speaker:Wistful Woman"},{"#":"portrait:npc8_happy"},{"#":"layout:left"},"\n","^That sounds nice. ",{"#":"speaker: Peyton"},{"#":"portrait:mc_happy"},{"#":"layout:right"},"\n","^It is, I enjoy the sounds of the train. ",{"#":"speaker:Wistful Woman"},{"#":"portrait:npc8_neutral"},{"#":"layout:left"},"\n","^Me too. ",{"#":"speaker: Peyton"},{"#":"portrait:mc_happy"},{"#":"layout:right"},"\n","^… ",{"#":"speaker:Wistful Woman"},{"#":"portrait:npc8_neutral"},{"#":"layout:left"},"\n","^… ",{"#":"speaker: Peyton"},{"#":"portrait:mc_happy"},{"#":"layout:right"},"\n","ev","str","^3","/str","/ev",{"VAR=":"wistful_current_dialogue","re":true},"end",{"#f":1}],"wistful_third_talk":["^Where are you travelling to my dear? ",{"#":"speaker:Wistful Woman"},{"#":"portrait:npc8_neutral"},{"#":"layout:left"},{"#":"character:npc8"},"\n","^Just to Stonefolk for a few days. Mundane appointments and stuff, picking things up in the city I can’t get elsewhere, nothing really exciting. ",{"#":"speaker: Peyton"},{"#":"portrait:mc_happy"},{"#":"layout:right"},"\n","^Though I guess you know exactly what that’s like. ",{"#":"speaker: Peyton"},{"#":"portrait:mc_happy"},{"#":"layout:right"},"\n","^I do. ",{"#":"speaker:Wistful Woman"},{"#":"portrait:npc8_happy"},{"#":"layout:left"},"\n","^Are you going to try to do anything nice while there? Even for a short while? ",{"#":"speaker:Wistful Woman"},{"#":"portrait:npc8_happy"},{"#":"layout:left"},"\n","^I am going to maybe catch some coffee with friends. ",{"#":"speaker: Peyton"},{"#":"portrait:mc_happy"},{"#":"layout:right"},"\n","^And maybe spend a night or two with another… friend. ",{"#":"speaker: Peyton"},{"#":"portrait:mc_happy"},{"#":"layout:right"},"\n","^Mmm, that sounds lovely. ",{"#":"speaker:Wistful Woman"},{"#":"portrait:npc8_happy"},{"#":"layout:left"},"\n","^I really cherish the small moments with friends I get to have. ",{"#":"speaker:Wistful Woman"},{"#":"portrait:npc8_happy"},{"#":"layout:left"},"\n","^Travelling so much I don’t get to see them often. ",{"#":"speaker:Wistful Woman"},{"#":"portrait:npc8_sad"},{"#":"layout:left"},"\n","^Aw, I’m sorry to hear that! ",{"#":"speaker: Peyton"},{"#":"portrait:mc_sad"},{"#":"layout:right"},"\n","^I hope the people you work with are at least fun to be around. ",{"#":"speaker: Peyton"},{"#":"portrait:mc_happy"},{"#":"layout:right"},"\n","^Unfortunately they aren’t. ",{"#":"speaker:Wistful Woman"},{"#":"portrait:npc8_sad"},{"#":"layout:left"},"\n","^I have work friends and they are fine company. People I see at offices all over and sometimes people I even travel with but…",{"#":"speaker:Wistful Woman"},{"#":"portrait:npc8_neutral"},{"#":"layout:left"},"\n","^Those aren’t real friendships because they are built on the foundation of work. ",{"#":"speaker:Wistful Woman"},{"#":"portrait:npc8_neutral"},{"#":"layout:left"},"\n","^We don’t have a lot of things in common, we don’t even share the same tastes in food. ",{"#":"speaker:Wistful Woman"},{"#":"portrait:npc8_neutral"},{"#":"layout:left"},"\n","^So I spend a lot of time with them while I’m working but while I’m abroad I still find myself eating alone and going to movies or concerts alone if I have the time. ",{"#":"speaker:Wistful Woman"},{"#":"portrait:npc8_sad"},{"#":"layout:left"},"\n","^It’s a little… Difficult… Spending so much time with people you don’t reall connect with. ",{"#":"speaker:Wistful Woman"},{"#":"portrait:npc8_sad"},{"#":"layout:left"},"\n","^It makes me miss my friends and the people I feel I’m leaving behind. ",{"#":"speaker:Wistful Woman"},{"#":"portrait:npc8_neutral"},{"#":"layout:left"},"\n","^That sounds really hard… ",{"#":"speaker: Peyton"},{"#":"portrait:mc_sad"},{"#":"layout:right"},"\n","^Maybe you could… take a break? ",{"#":"speaker: Peyton"},{"#":"portrait:mc_happy"},{"#":"layout:right"},"\n","^Even for just a little? ",{"#":"speaker: Peyton"},{"#":"portrait:mc_happy"},{"#":"layout:right"},"\n","^I’ve been thinking about it… ",{"#":"speaker:Wistful Woman"},{"#":"portrait:npc8_neutral"},{"#":"layout:left"},"\n","^I often think I’ll take a break when the work slows down but– ",{"#":"speaker:Wistful Woman"},{"#":"portrait:npc8_neutral"},{"#":"layout:left"},"\n","^<i>Laughs.</i> ",{"#":"speaker:Wistful Woman"},{"#":"portrait:npc8_happy"},{"#":"layout:left"},"\n","^That’s the thing! ",{"#":"speaker:Wistful Woman"},{"#":"portrait:npc8_happy"},{"#":"layout:left"},"\n","^It never slows down! ",{"#":"speaker:Wistful Woman"},{"#":"portrait:npc8_sad"},{"#":"layout:left"},"\n","^That… really sucks. ",{"#":"speaker: Peyton"},{"#":"portrait:mc_sad"},{"#":"layout:right"},"\n","^It does! ",{"#":"speaker:Wistful Woman"},{"#":"portrait:npc8_sad"},{"#":"layout:left"},"\n","^I’ve just tried getting small moments of joy and rest here and there to sustain me, but I fear the small moments aren’t going to last. ",{"#":"speaker:Wistful Woman"},{"#":"portrait:npc8_neutral"},{"#":"layout:left"},"\n","^You definitely need a break. ",{"#":"speaker: Peyton"},{"#":"portrait:mc_happy"},{"#":"layout:right"},"\n","^I definitely do. ",{"#":"speaker:Wistful Woman"},{"#":"portrait:npc8_neutral"},{"#":"layout:left"},"\n","^Perhaps after this next appointment I’ll take some time off and head back home. ",{"#":"speaker:Wistful Woman"},{"#":"portrait:npc8_neutral"},{"#":"layout:left"},"\n","^I really think you should do that. ",{"#":"speaker: Peyton"},{"#":"portrait:mc_happy"},{"#":"layout:right"},"\n","^Mm, I think so too. ",{"#":"speaker:Wistful Woman"},{"#":"portrait:npc8_neutral"},{"#":"layout:left"},"\n","^Thank you. ",{"#":"speaker:Wistful Woman"},{"#":"portrait:npc8_neutral"},{"#":"layout:left"},"\n","^Hey, no worries. ",{"#":"speaker: Peyton"},{"#":"portrait:mc_happy"},{"#":"layout:right"},"\n","^We all need breaks. ",{"#":"speaker: Peyton"},{"#":"portrait:mc_happy"},{"#":"layout:right"},"\n","^Indeed we do. ",{"#":"speaker:Wistful Woman"},{"#":"portrait:npc8_happy"},{"#":"layout:left"},"\n","^… ",{"#":"speaker:Wistful Woman"},{"#":"portrait:npc8_neutral"},{"#":"layout:left"},"\n","^… ",{"#":"speaker: Peyton"},{"#":"portrait:mc_happy"},{"#":"layout:right"},"\n","^… ",{"#":"speaker:Wistful Woman"},{"#":"portrait:npc8_neutral"},{"#":"layout:left"},"\n","ev","str","^4","/str","/ev",{"VAR=":"wistful_current_dialogue","re":true},"end",{"#f":1}],"wistful_fourth_talk":["^Thank you for chatting me, it is a refreshing change to be so honest with someone. ",{"#":"speaker:Wistful Woman"},{"#":"portrait:npc8_happy"},{"#":"layout:left"},{"#":"character:npc8"},"\n","^Oh, yeah no problem! ",{"#":"speaker: Peyton"},{"#":"portrait:mc_happy"},{"#":"layout:right"},"\n","^No better person than a stranger to tell all your problems to. ",{"#":"speaker: Peyton"},{"#":"portrait:mc_happy"},{"#":"layout:right"},"\n","^You’re right about that. ",{"#":"speaker:Wistful Woman"},{"#":"portrait:npc8_happy"},{"#":"layout:lef"},"\n","^Shall we enjoy the scenery for a bit? ",{"#":"speaker: Peyton"},{"#":"portrait:mc_happy"},{"#":"layout:right"},"\n","^Yes, please. ",{"#":"speaker:Wistful Woman"},{"#":"portrait:npc8_happy"},{"#":"layout:lef"},"\n","^… ",{"#":"speaker: Peyton"},{"#":"portrait:mc_happy"},{"#":"layout:right"},"\n","^… ",{"#":"speaker:Wistful Woman"},{"#":"portrait:npc8_happy"},{"#":"layout:lef"},"\n","^… ",{"#":"speaker: Peyton"},{"#":"portrait:mc_happy"},{"#":"layout:right"},"\n","^… ",{"#":"speaker:Wistful Woman"},{"#":"portrait:npc8_happy"},{"#":"layout:lef"},"\n","ev","str","^5","/str","/ev",{"VAR=":"wistful_current_dialogue","re":true},"ev",{"VAR?":"ending"},1,"+","/ev",{"VAR=":"ending","re":true},"end",{"#f":1}],"wistful_final_talk":["^<i>You can see her sitting with her eyes closed, you are unsure if she is asleep or not, but decide not to disturb her regardless.</i> ",{"#":"character:npc8"},"\n","end",{"#f":1}],"global decl":["ev","str","^","/str",{"VAR=":"busker_current_dialogue"},"str","^","/str",{"VAR=":"tired_current_dialogue"},"str","^","/str",{"VAR=":"hypebeast_current_dialogue"},"str","^","/str",{"VAR=":"bashful_current_dialogue"},"str","^","/str",{"VAR=":"mother_current_dialogue"},"str","^","/str",{"VAR=":"commuter_current_dialogue"},"str","^","/str",{"VAR=":"clutter_current_dialogue"},"str","^","/str",{"VAR=":"dressed_current_dialogue"},"str","^","/str",{"VAR=":"wistful_current_dialogue"},"str","^","/str",{"VAR=":"fire_current_dialogue"},"str","^","/str",{"VAR=":"skeleton_current_dialogue"},"str","^","/str",{"VAR=":"statue_current_dialogue"},"str","^","/str",{"VAR=":"plant_current_dialogue"},"str","^","/str",{"VAR=":"busker_end"},"str","^","/str",{"VAR=":"hypebeast_end"},"str","^","/str",{"VAR=":"bashful_end"},"str","^","/str",{"VAR=":"tired_end"},"str","^","/str",{"VAR=":"commuter_end"},"str","^","/str",{"VAR=":"mother_end"},"str","^","/str",{"VAR=":"clutter_end"},"str","^","/str",{"VAR=":"dressed_end"},"str","^","/str",{"VAR=":"wistful_end"},"str","^","/str",{"VAR=":"fire_end"},"str","^","/str",{"VAR=":"skeleton_end"},"str","^","/str",{"VAR=":"statue_end"},"str","^","/str",{"VAR=":"plant_end"},0,{"VAR=":"ending"},"/ev","end",null],"#f":1}],"listDefs":{}}